kik/__init__.py
kik.py-1.0.0.dist-info/LICENSE
kik.py-1.0.0.dist-info/METADATA
kik.py-1.0.0.dist-info/WHEEL
kik.py-1.0.0.dist-info/top_level.txt
kik.py-1.0.0.dist-info/RECORD
