Metadata-Version: 2.1
Name: kik.py
Version: 1.0.0
Summary: Library for Kik. Discord - https://discord.gg/Bf3dpBRJHj
Home-page: UNKNOWN
Author: Minori
Author-email: 
License: MIT
Keywords: aminoapps,kik,kik-bot,narvii,api,python,python3,python3.x,minori
Platform: UNKNOWN
Requires-Python: >=3.6
License-File: LICENSE
Requires-Dist: requests
Requires-Dist: json-minify
Requires-Dist: six
